rofehcloud/__init__.py
rofehcloud/__main__.py
rofehcloud/__version__
rofehcloud/agent.py
rofehcloud/aws.py
rofehcloud/chat.py
rofehcloud/config.py
rofehcloud/constants.py
rofehcloud/llm.py
rofehcloud/logger.py
rofehcloud/profile.py
rofehcloud/utils.py
rofehcloud-0.6.2.dist-info/LICENSE.txt
rofehcloud-0.6.2.dist-info/METADATA
rofehcloud-0.6.2.dist-info/WHEEL
rofehcloud-0.6.2.dist-info/entry_points.txt
rofehcloud-0.6.2.dist-info/top_level.txt
rofehcloud-0.6.2.dist-info/RECORD
