Metadata-Version: 2.1
Name: rofehcloud
Version: 0.6.2
Summary: AI-powered CLI tool for automatic troubleshooting of complex systems based on Kubernetes, public and private clouds like AWS, Google Cloud (GCP), Azure, OpenStack, etc
Author-email: Team <team@rofehcloud.com>
License: Mozilla Public License 2.0 (MPL 2.0)
Project-URL: Homepage, https://github.com/rofehcloud/rofehcloud
Project-URL: Issues, https://github.com/rofehcloud/rofehcloud/issues
Classifier: Programming Language :: Python :: 3
Classifier: License :: OSI Approved :: Mozilla Public License 2.0 (MPL 2.0)
Classifier: Operating System :: OS Independent
Requires-Python: >=3.10
License-File: LICENSE.txt
Requires-Dist: pyyaml ==6.0.2
Requires-Dist: colorama ==0.4.6
Requires-Dist: tzlocal ==5.2
Requires-Dist: questionary ==2.0.1
Requires-Dist: python-dotenv ==1.0.1
Requires-Dist: langchain ==0.3.4
Requires-Dist: langchain-openai ==0.2.3
Requires-Dist: langchainhub ==0.1.21
Requires-Dist: langchain-community ==0.3.3
Requires-Dist: langchain-aws ==0.2.6
Requires-Dist: boto3 ==1.35.45
Requires-Dist: rich ==13.9.4
Requires-Dist: cerberus ==1.3.5
